counter.v
module counter;
  reg clk = 0;
  reg [3:0] out = 0;

  always #5 clk = ~clk;

  always @(posedge clk)
    out = out + 1;

  initial begin
    $dumpfile("counter.vcd");
    $dumpvars(0, counter);
    #100 $finish;
  end
endmodule

counter.vcd
$date
	Sat Feb 07 14:53:48 2026
$end
$version
	Icarus Verilog
$end
$timescale
	1s
$end
$scope module counter $end
$var reg 1 ! clk $end
$var reg 4 " out [3:0] $end
$upscope $end
$enddefinitions $end
$comment Show the parameter values. $end
$dumpall
$end
#0
$dumpvars
b0 "
0!
$end
#5
b1 "
1!
#10
0!
#15
b10 "
1!
#20
0!
#25
b11 "
1!
#30
0!
#35
b100 "
1!
#40
0!
#45
b101 "
1!
#50
0!
#55
b110 "
1!
#60
0!
#65
b111 "
1!
#70
0!
#75
b1000 "
1!
#80
0!
#85
b1001 "
1!
#90
0!
#95
b1010 "
1!
